{
  "verse_reference": "MT 5:34",
  "verse_text": "Verse text for MT 5:34",
  "scraped_with": "Hybrid approach (Firecrawl + BeautifulSoup)",
  "extraction_date": "2025-09-11",
  "source_url": "https://catenabible.com/mt/5/34",
  "commentary_status": "available",
  "total_commentaries": 5,
  "full_content_fetched": 5,
  "commentaries": [
    {
      "author": "Augustine of Hippo",
      "period": "AD430",
      "content": "But it may be asked why, when it was said, But I say unto you, Swear not at all, it was added, neither by heaven, for it is God's throne, etc. , up to neither by your head. I suppose it was for this reason, that the Jews did not think they were bound by the oath, if they had sworn by such things: and since they had heard it said, You shall perform unto the Lord your oath, they did not think an oath brought them under obligation to the Lord, if they swore by heaven, or earth, or by Jerusalem, or by their head; and this happened not from the fault of Him who gave the command, but because they did not rightly understand it. Hence the Lord teaches that there is nothing so worthless among the creatures of God, as that any one should think that he may swear falsely by it; since created things, from the highest down to the lowest, beginning with the throne of God and going down to a white or black hair, are ruled by divine providence. Neither by heaven, says He, for it is God's throne; nor by the earth, for it is His footstool: i. , when you swear by heaven or the earth, do not imagine that your oath does not bring you under obligation to the Lord; for you are convicted of swearing by Him who has heaven for His throne, and the earth for His footstool. Neither by Jerusalem, for it is the city of the great King; a better expression than if He had said, My [city]; although, however, we understand Him to have meant this. And, because He is undoubtedly the Lord, the man who swears by Jerusalem is bound by his oath to the Lord. Neither shall you swear by your head. Now, what could any one suppose to belong more to himself than his own head. But how is it ours, when we have not the power of making one hair white or black. Hence, whoever should wish to swear even by his own head, is bound by his oath to God, who in an ineffable way keeps all things in His power, and is everywhere present. And here also all other things are understood, which could not of course be enumerated; just as that saying of the apostle we have mentioned, By your rejoicing, I die daily. And to show that he was bound by this oath to the Lord, he has added, which I have in Christ Jesus. But yet (I make the remark for the sake of the carnal) we must not think that heaven is called God's throne, and the earth His footstool, because God has members placed in heaven and in earth, in some such way as we have when we sit down; but that seat means judgment. And since, in this organic whole of the universe, heaven has the greatest appearance, and earth the least—as if the divine power were more present where the beauty excels, but still were regulating the least degree of it in the most distant and in the lowest regions—He is said to sit in heaven, and to tread upon the earth. But spiritually the expression heaven means holy souls, and earth sinful ones: and since the spiritual man judges all things, yet he himself is judged of no man, he is suitably spoken of as the seat of God; but the sinner to whom it is said, Earth you are, and unto earth shall you return, because, in accordance with that justice which assigns what is suitable to men's deserts, he is placed among things that are lowest, and he who would not remain in the law is punished under the law, is suitably taken as His footstool.",
      "commentary_number": "1/5",
      "reading_time": "3 mins",
      "source_url": "https://catenabible.com/mt/5/34",
      "full_content_url": "https://catenabible.com/com/57eb0f15b0d44ee10cfac752",
      "content_type": "full",
      "extraction_method": "firecrawl"
    },
    {
      "author": "Chromatius of Aquileia",
      "period": "AD407",
      "content": "By the grace of gospel teaching, the law given by Moses acquired an advantage. The law prescribes that one must not swear falsely; but according to the gospel one must not swear at all. The Holy Spirit had seen fit to order this through Solomon when he said, “Do not accustom your mouth to oaths. ” And again: “Even as a wellchastised servant is not deterred from envy, whoever swears and does business will not be purged from sin. ” Therefore it is absolutely inappropriate for us to swear. What need is there for us to swear when we are not allowed to lie at all and our words must always be true and trustworthy, so much so that they may be taken as an oath. On this, the Lord not only forbids us to swear falsely but even to swear, lest we appear to tell the truth only when we swear and lest (while we should be truthful in our every word) we think it is all right to lie when we do not take an oath. For this is the purpose of an oath: Everyone who swears, swears to the fact what he is saying is true. Therefore the Lord does not want a gap between our oath and our ordinary speech. Even as there must be no faithlessness in an oath, in our words there must be no lie. For both false swearing and lying are punished with divine judgment, as the Scripture says: “The mouth that lies kills the soul. ” So whoever speaks the truth swears, for it is written: “A faithful witness will not lie.",
      "commentary_number": "2/5",
      "reading_time": "1 min",
      "source_url": "https://catenabible.com/mt/5/34",
      "full_content_url": "https://catenabible.com/com/585b63219ac03ecd4b8e6da9",
      "content_type": "full",
      "extraction_method": "firecrawl"
    },
    {
      "author": "Cornelius a Lapide",
      "period": "AD1637",
      "content": "But I say unto you, &c. Christ here explains and perfects the third precept of the Decalogue, which the Scribes and Pharisees had explained falsely. they asserted that an oath became an oath, and was binding, if it were made by God, and called Him to witness, but not so if it were sworn by creatures. Christ here teaches the contrary. For in creatures the Creator is understood, for they were made by God, and all that they have and are is from God. For he who swears, calls God, who is the prime Verity, to witness his oath. He therefore who swears by a creature, either makes that creature a God, which is the sin of idolatry, or else it behoves to understand God the Creator in the oath. The Scribes erred, who thought that by this precept perjury only was forbidden. On the contrary Christ here teaches that by it every oath is forbidden, all irreverence and abuse of the name of God. From this passage, the Pelagians, as S. Augustine testifies (Epist89 , q5. ) taught that no oath was lawful for Christians. The Waldenses thought the same, as we see from the Council of Constance, and the Anabaptists of the present day hold the same opinion, who will not swear in a trial at the bidding of the judge. But this is an error of faith, which the perpetual practice of the Church, as well as the example of God Himself, of S. Paul, and the Saints condemns, as is plain from Psalm 110:4; Romans 1:9; Philippians 1:8; 1 Corinthians 15:31, &c. Reason itself shows us the same thing; for an oath is an honour to God as the prime Verity, because he who swears appeals to Infallible Truth as his witness. Wherefore an oath is an act of religion, and the highest worship, so that it be done in truth and justice, as Jeremiah says, 4:2. You will ask, Why, then, does Christ say, Swear not at all. Bernard answers (Serm65 in Cant. ) that this is not of precept, but only of counsel. Others allow that this is a precept, but one which only forbids perjury. Others think that the command, Swear not at all, applies only to swearing by creatures, not by God. To this opinion S. Jerome inclines. But all these explanations are forced and incorrect, and are refuted by what follows; for Christ bids us swear not at all, (1) because, as S. Augustine says (de Verb. Apostoli), \"False swearing is destructive, true swearing is perilous, swearing not at all is safe. \" Not at all—i. e, \"As far as lieth in thee, that thou shouldst not affect nor love swearing, nor take any pleasure in an oath, as though it were a good thing. \" Again, to swear Isaiah , per se, a moral evil of irreverence with respect to God; just as it is a moral evil, per se, to kill any one; yet there are cases in which it is a duty. So it is with an oath. In Paradise it was not lawful to swear, nor will it be lawful in heaven. So great is the majesty of the Name of God that It must not be called to witness unless necessity compel. For to invoke It about small and worthless things is to make It small and vile, just as would be the action of one who should call the king as witness about a single guinea. Hence the saints were cautious about swearing. In the Life of S. Chrysostom it is recorded as a notable thing that he never swore. The same is testified of S. John the Almoner. You will ask whether also for Christians it is lawful to swear. For (1) many of the Fathers seem to say that it is not. Jerome, Chrysostom, Euthymius, say that swearing was permitted by God to the Jews, lest they should swear by idols, but is not permitted to Christians. (2) Theophylact and Euthymius are of opinion that an oath was a legal precept of the old law, like circumcision. Wherefore, as the latter has been done away by Christ, so has the former. (3) Others think that an oath was allowed by God to the Jews, as being uninstructed, imperfect, and hard of belief, but has been forbidden to Christians because more perfect things become them as being more perfect, and because they ought to beware of the slightest peril of perjury. That in the same way divorce was permitted to the Jews, lest they should kill the wives whom they hated; and yet Christ takes away this permission from Christians. Thus think S. Hilary (in loc, Can4), S. Ambrose (in Psalm 119 , Serm1), S. Basil (in Psalm 13), Chromatius and Origen (in loc, Tract35), Epiphanius (Hres19), S. Athanasius (Serm. de Passione et Cruce Domini), S. Chrysostom (Hom. If you object that in Holy Scripture God took an oath, as in Genesis 22:16, SS. Athanasius, Basil, and Ambrose answer that such oaths of God were not strictly speaking oaths, but. asseverations only—or promises; or, as S. Ambrose says, God may swear because He is able to fulfil that which He swears, and He cannot repent of it. But a man ought not to swear because he has not any certain power of doing that to which he pledges his oath. If, further, you object that surely S. Paul swore when he said ( 2 Corinthians 1:23), \"I call God to witness upon my soul\" (Vulg. Basil answers that this is not really an oath, but only a simple mode of speech, uttered with the appearance and form of an oath as a stronger affirmation. But I say that not to the Jews only, but to Christians, is it lawful to swear. This is of faith, as is plain from the perpetual sense, use, and practice of the Church. \"For of all strife among men\"—even Christians—\"an oath for confirmation is the end,\" says the Apostle to the Hebrews 6:16. Moreover, in Scripture there is no affirmative precept for swearing, as there is for praying, sacrificing, loving and praising God, honouring parents, &c, because an oath is not, per se, desirable, but only for the sake of something else, and, as it were, per accidens, in such sort that it is a kind of medicine for unbelief. And there is a negative precept for swearing, namely that you shall not commit perjury or swear by false gods, but only by the true God. There is also a conditional precept that if you swear you shall only swear what is just, true, and necessary. You may say, Christ here solemnly says to Christians, Swear not at all. I answer, this is true because, per se, it is unbecoming and improper to call the Great and Good God to witness about human disputes on account of men\"s mutual distrusts, unless this impropriety may be excused by mutual necessity, as it is often excused by the want of witnesses and other judicial proofs. To the Fathers who have been cited, I reply that they seem to have spoken in the same sense that Christ did, because they saw men often swearing falsely or unjustly, and, still more frequently, lightly, foolishly and rashly; hence on account of the peril of these things, they forbade an oath to Christians, that they should refrain from it as much as possible. But if any one is careful to avoid such dangers, then it is lawful for him to swear in a case of necessity. This is plain from S. Chrysostom, who, in his homilies to the people of Antioch, frequently and sharply rebuked their habit of rash swearing. And to those who wondered at his so doing, he thus replies. \"I say and repeat, as I am accustomed, because ye say and repeat what ye are accustomed. \" And he declares that he will not cease from this repetition until they leave off swearing. \"For a hard knot a hard and constant wedge must be used. \" Neither by heaven, &c. It seems that the Jews were wont to swear by heaven and earth, and similar oaths. And because the Pharisees thought that these oaths, being made by creatures, were of small account, Christ here teaches the contrary—viz, that he who swears by heaven or earth, swears by God their Creator, who has placed the throne of His glory in heaven, and his footstool on earth.",
      "commentary_number": "3/5",
      "reading_time": "7 mins",
      "source_url": "https://catenabible.com/mt/5/34",
      "full_content_url": "https://catenabible.com/com/5838d8f6205c248f42e51d34",
      "content_type": "full",
      "extraction_method": "firecrawl"
    },
    {
      "author": "George Leo Haydock",
      "period": "AD1849",
      "content": "Swear not at all. We must not imagine that here are forbidden all oaths, where there is a just and necessary cause of calling God to witness. An oath on such an occasion is an act of justice and religion. Here are forbidden unnecessary oaths in common discourse, by which the sacred name of God, which never ought to be pronounced without reverence and respect, is so frequently and scandalously profaned. (Witham)\n'Tis not forbidden to swear in truth, justice and judgment; to the honour of God, or our own or neighbours' just defence; but only to swear rashly, or profanely, in common discourse, and without necessity. (Challoner)",
      "commentary_number": "4/5",
      "reading_time": "1 min",
      "source_url": "https://catenabible.com/mt/5/34",
      "full_content_url": "https://catenabible.com/com/5735e2b1ec4bd7c9723bf697",
      "content_type": "full",
      "extraction_method": "beautifulsoup"
    },
    {
      "author": "John Chrysostom",
      "period": "AD407",
      "content": "But I say unto you, Swear not at all; neither by heaven; for it is God's throne: Next, to lead them farther away from swearing by God, He says, Neither by Heaven, for it is God's throne, nor by the earth, for it is the footstool of His feet; nor by Jerusalem, for it is the city of the great King: still speaking out of the prophetical writings, and signifying Himself not to be opposed to the ancients. This was because they had a custom of swearing by these objects, and he intimates this custom near the end of his Gospel.",
      "commentary_number": "5/5",
      "reading_time": "< 1 min",
      "source_url": "https://catenabible.com/mt/5/34",
      "full_content_url": "https://catenabible.com/com/57eb0db6b0d44ee10cfac33d",
      "content_type": "full",
      "extraction_method": "beautifulsoup"
    }
  ],
  "methodology": {
    "step_1": "Parse main page with BeautifulSoup for structure",
    "step_2": "Extract metadata (author, period, reading time)",
    "step_3": "Use Firecrawl to get full content from 'Go to Commentary' links",
    "step_4": "Fallback to BeautifulSoup for accordion content if needed",
    "result": "Successfully captured MT 5:34",
    "advantages": [
      "Complete commentary content via Firecrawl",
      "Structured metadata extraction",
      "Robust fallback mechanisms",
      "Records verses even without commentaries for complete tracking"
    ]
  }
}