{
  "verse_reference": "PRV 3:35",
  "book": "prv",
  "chapter": 3,
  "verse": 35,
  "commentary_status": "available",
  "total_commentaries": 3,
  "commentaries": [
    {
      "author": "George Leo Haydock",
      "period": "AD1849",
      "content": "Disgrace. They are seen by more, and their fall is more dangerous. (Calmet)\n\"A fool extols what is ignominious. \"(Pagnin) (Haydock)"
    },
    {
      "author": "Hippolytus of Rome",
      "period": "AD235",
      "content": "1 Esdras Wisdom of Solomon Wisdom of Sirach Epistle of Jeremiah Prayer of Manasseh The wise shall inherit glory: but shame shall be the recompense of fools. Hippolytus of Rome They will not simply obtain glory but inherit wisdom. The wicked, again, even though they are exalted, are exalted only so as to have greater dishonor. For as one does not honor someone who is ugly and misshapen, if he exalts him, but only dishonors him the more by making his shame manifest to a larger number; so also God exalts the wicked, in order that he may make their disgrace obvious. For pharaoh was exalted, but only to have the world as his accuser."
    },
    {
      "author": "Hippolytus of Rome",
      "period": "AD235",
      "content": "1 Esdras Wisdom of Solomon Wisdom of Sirach Epistle of Jeremiah Prayer of Manasseh The wise shall inherit glory: but shame shall be the recompense of fools. Hippolytus of Rome They will not simply obtain, but inherit. The wicked, again, even though they are exalted, are exalted only so as to have greater dishonour. For as one does not honour an ugly and misshapen fellow, if he exalts him, but only dishonours him the more, by making his shame manifest to a larger number; so also God exalts the wicked, in order that He may make their disgrace patent. For Pharaoh was exalted, but only to have the world as his accuser."
    }
  ]
}