{
  "verse_reference": "OB 1:2",
  "book": "ob",
  "chapter": 1,
  "verse": 2,
  "commentary_status": "available",
  "total_commentaries": 2,
  "commentaries": [
    {
      "author": "Ephrem The Syrian",
      "period": "AD373",
      "content": "Obadiah shows here that the Edomites must be subjected to captivity because of their pride and the enmity they held against their brothers. In a different sense he says that the devil is made least, as the words that follow are extremely suitable to him as well. ."
    },
    {
      "author": "George Leo Haydock",
      "period": "AD1849",
      "content": "Contemptible. The nations of Chaldea, were far more potent. Yet Edom must be brought still lower."
    }
  ]
}