{
  "verse_reference": "IS 53:8",
  "verse_text": "Verse text for IS 53:8",
  "scraped_with": "Hybrid approach (Firecrawl + BeautifulSoup)",
  "extraction_date": "2025-09-18",
  "source_url": "https://catenabible.com/is/53/8",
  "commentary_status": "available",
  "total_commentaries": 1,
  "full_content_fetched": 1,
  "commentaries": [
    {
      "author": "George Leo Haydock",
      "period": "AD1849",
      "content": "1 Esdras Wisdom of Solomon Wisdom of Sirach Epistle of Jeremiah Prayer of Manasseh He was taken from prison and from judgment: and who shall declare his generation. for he was cut off out of the land of the living: for the transgression of my people was he stricken. Judgment, or by an unjust and cruel judgment. (Haydock) Hebrew, \"from prison and judgment. \"(Calmet) Septuagint, \"in humiliation, (Haydock) or humility, his judgment was taken away \"or rescinded, by his glorious resurrection. Philip follows this version in explaining this passage to the eunuch, Acts viii. Generation, from his eternal Father or from the Virgin , his incarnation, life, resurrection, or posterity in the Church. All these may be meant, and are inexplicable.",
      "commentary_number": "1/1",
      "reading_time": "< 1 min",
      "source_url": "https://catenabible.com/is/53/8",
      "full_content_url": "https://catenabible.com/com/5735e264ec4bd7c9723beb5e",
      "content_type": "full",
      "extraction_method": "beautifulsoup"
    }
  ],
  "methodology": {
    "step_1": "Parse main page with BeautifulSoup for structure",
    "step_2": "Extract metadata (author, period, reading time)",
    "step_3": "Use Firecrawl to get full content from 'Go to Commentary' links",
    "step_4": "Fallback to BeautifulSoup for accordion content if needed",
    "result": "Successfully captured IS 53:8",
    "advantages": [
      "Complete commentary content via Firecrawl",
      "Structured metadata extraction",
      "Robust fallback mechanisms",
      "Records verses even without commentaries for complete tracking"
    ]
  }
}