{
  "verse_reference": "MK 4:17",
  "verse_text": "Verse text for MK 4:17",
  "scraped_with": "Hybrid approach (Firecrawl + BeautifulSoup)",
  "extraction_date": "2025-09-11",
  "source_url": "https://catenabible.com/mk/4/17",
  "commentary_status": "available",
  "total_commentaries": 1,
  "full_content_fetched": 1,
  "commentaries": [
    {
      "author": "Athanasius the Apostolic",
      "period": "AD373",
      "content": "Let us, therefore, following the faith of the apostles, hol frequent communion with our Lor. For the worl is like the sea to us, belove, of which it is written, “There go the ships, an Leviathan that you forme to sport in it.” We float upon this sea, like win, with everyone irecting his own course with his own free will. Uner the pilotage of the Wor, one may safely approach the port. But, if possesse by waywar inclinations, one is in peril by storm an may suffer shipwreck. For as in the ocean there are storms an waves, so in the worl there are many afflictions an trials. The unbelieving therefore, “have no root in themselves, but enure for a while; then, when tribulation or persecution arises on account of the wor, immeiately they fall away,” just as the Lor sai. They are not likely to enure the complications which arise from afflictions, if they are fixe upon the temporal an not confirme in the faith. Letter, Easter a..",
      "commentary_number": "1/1",
      "reading_time": "1 min",
      "source_url": "https://catenabible.com/mk/4/17",
      "full_content_url": "https://catenabible.com/com/5838fee5205c248f42e52d26",
      "content_type": "full",
      "extraction_method": "beautifulsoup"
    }
  ],
  "methodology": {
    "step_1": "Parse main page with BeautifulSoup for structure",
    "step_2": "Extract metadata (author, period, reading time)",
    "step_3": "Use Firecrawl to get full content from 'Go to Commentary' links",
    "step_4": "Fallback to BeautifulSoup for accordion content if needed",
    "result": "Successfully captured MK 4:17",
    "advantages": [
      "Complete commentary content via Firecrawl",
      "Structured metadata extraction",
      "Robust fallback mechanisms",
      "Records verses even without commentaries for complete tracking"
    ]
  }
}