{
  "verse_reference": "1CHR 21:5",
  "verse_text": "Verse text for 1CHR 21:5",
  "scraped_with": "Hybrid approach (Firecrawl + BeautifulSoup)",
  "extraction_date": "2026-03-14",
  "source_url": "https://catenabible.com/1chr/21/5",
  "commentary_status": "available",
  "total_commentaries": 2,
  "full_content_fetched": 2,
  "commentaries": [
    {
      "author": "George Leo Haydock",
      "period": "AD1849",
      "content": "1 Esdras Wisdom of Solomon Wisdom of Sirach Epistle of Jeremiah Prayer of Manasseh 1 Chronicles 21:5 And Joab gave the sum of the number of the people unto David. And all they of Israel were a thousand thousand and a hundred thousand men that drew sword: and Judah was four hundred threescore and ten thousand men that drew sword. The number The difference of the numbers here and 2 Kings xxiv. , is to be accounted for, by supposing the greater number to be that which was really found, and the lesser to be that which Joab gave in; (Challoner) or the transcribers of this place have been inaccurate.",
      "commentary_number": "1/2",
      "reading_time": "< 1 min",
      "source_url": "https://catenabible.com/1chr/21/5",
      "full_content_url": "https://catenabible.com/com/5735e1bcec4bd7c9723bd6fc",
      "content_type": "full",
      "extraction_method": "beautifulsoup"
    },
    {
      "author": "Richard Challoner",
      "period": "AD1781",
      "content": "1 Esdras Wisdom of Solomon Wisdom of Sirach Epistle of Jeremiah Prayer of Manasseh 1 Chronicles 21:5 And Joab gave the sum of the number of the people unto David. And all they of Israel were a thousand thousand and a hundred thousand men that drew sword: and Judah was four hundred threescore and ten thousand men that drew sword. The difference of the numbers here and 2 Kings 24. is to be accounted for, by supposing the greater number to be that which was really found, and the lesser to be that which Joab gave in.",
      "commentary_number": "2/2",
      "reading_time": "< 1 min",
      "source_url": "https://catenabible.com/1chr/21/5",
      "full_content_url": "https://catenabible.com/com/5879d89fdd1bb6dd3dba9fa9",
      "content_type": "full",
      "extraction_method": "beautifulsoup"
    }
  ],
  "methodology": {
    "step_1": "Parse main page with BeautifulSoup for structure",
    "step_2": "Extract metadata (author, period, reading time)",
    "step_3": "Use Firecrawl to get full content from 'Go to Commentary' links",
    "step_4": "Fallback to BeautifulSoup for accordion content if needed",
    "result": "Successfully captured 1CHR 21:5",
    "advantages": [
      "Complete commentary content via Firecrawl",
      "Structured metadata extraction",
      "Robust fallback mechanisms",
      "Records verses even without commentaries for complete tracking"
    ]
  }
}