{
  "verse_reference": "IS 45:4",
  "book": "is",
  "chapter": 45,
  "verse": 4,
  "commentary_status": "available",
  "total_commentaries": 1,
  "commentaries": [
    {
      "author": "George Leo Haydock",
      "period": "AD1849",
      "content": "Likeness of Christ.\nKnown me. Before the Jews had shown Cyrus the prophecies, he did not attribute his success to the Lord, and even afterwards he seems not to have left the superstitions of his country, as his sacrifices to idols are described. He resembled Nabuchodonosor and the philosophers, who did not glorify God according to their knowledge, Daniel ii. 47., and Romans i. 21. Cyrus even revoked the decree for building the temple, 1 Esdras iv. 5. (Calmet)\nHe believed there was one God; (1 Esdras i.) yet he did not embrace the truth entirely. (Worthington)"
    }
  ]
}