{
  "verse_reference": "ACTS 4:8",
  "book": "acts",
  "chapter": 4,
  "verse": 8,
  "commentary_status": "available",
  "total_commentaries": 2,
  "commentaries": [
    {
      "author": "Cyprian of Carthage",
      "period": "AD258",
      "content": "This is the stone which was despised by you builders, which has become the head of the corner. For there is no other name given to men under heaven in which we must be saved.\""
    },
    {
      "author": "Interlinear Gloss",
      "period": "AD1480",
      "content": "And now, I urge you, call to mind Christ’s saying; “When they deliver you up unto the synagogues, take no thought how or what thing you shall speak; for it is the Spirit of your Father which speaketh in you.\" (Lk 12:11-12)"
    }
  ]
}