{
  "verse_reference": "LK 21:26",
  "verse_text": "Verse text for LK 21:26",
  "scraped_with": "Hybrid approach (Firecrawl + BeautifulSoup)",
  "extraction_date": "2025-09-11",
  "source_url": "https://catenabible.com/lk/21/26",
  "commentary_status": "available",
  "total_commentaries": 2,
  "full_content_fetched": 2,
  "commentaries": [
    {
      "author": "George Leo Haydock",
      "period": "AD1849",
      "content": "Men's hearts failing them for fear, and for looking toward those things which are coming on the earth: for the powers of heaven shall be shaken. The powers of heaven Some explain this of the angels, who shall be terrified and tremble at the sight of so many calamities. Others understand it of the heavenly bodies, the sun, moon, stars which shall in some sort, likewise, be confused in the general dissolution. The prophets often make use of such expressions, when speaking of the fall of monarchies, or the ruin of nations. The heavens shall be astonished and moved (Ezechiel xxxii. 7; Joel iii.",
      "commentary_number": "1/2",
      "reading_time": "< 1 min",
      "source_url": "https://catenabible.com/lk/21/26",
      "full_content_url": "https://catenabible.com/com/5735e2caec4bd7c9723bfb58",
      "content_type": "full",
      "extraction_method": "beautifulsoup"
    },
    {
      "author": "Tertullian of Carthage",
      "period": "AD220",
      "content": "That \"the very powers also of heaven have to be shaken\"",
      "commentary_number": "2/2",
      "reading_time": "< 1 min",
      "source_url": "https://catenabible.com/lk/21/26",
      "full_content_url": "https://catenabible.com/com/5735e140ec4bd7c9723bbf4e",
      "content_type": "full",
      "extraction_method": "beautifulsoup"
    }
  ],
  "methodology": {
    "step_1": "Parse main page with BeautifulSoup for structure",
    "step_2": "Extract metadata (author, period, reading time)",
    "step_3": "Use Firecrawl to get full content from 'Go to Commentary' links",
    "step_4": "Fallback to BeautifulSoup for accordion content if needed",
    "result": "Successfully captured LK 21:26",
    "advantages": [
      "Complete commentary content via Firecrawl",
      "Structured metadata extraction",
      "Robust fallback mechanisms",
      "Records verses even without commentaries for complete tracking"
    ]
  }
}