{
  "verse_reference": "2CHR 12:12",
  "verse_text": "Verse text for 2CHR 12:12",
  "scraped_with": "Hybrid approach (Firecrawl + BeautifulSoup)",
  "extraction_date": "2026-03-14",
  "source_url": "https://catenabible.com/2chr/12/12",
  "commentary_status": "available",
  "total_commentaries": 1,
  "full_content_fetched": 1,
  "commentaries": [
    {
      "author": "George Leo Haydock",
      "period": "AD1849",
      "content": "For even. Protestants, \"and also in Judah things went well \"(Haydock) or, \"he spoke good words even to Juda. \"(Calmet)\nSeptuagint, \"for even in Juda there were good words, and in all pleasing. \"Words are often put for works. (Haydock)\nThe Lord regarded the fidelity of some, and the humility of the princes. (Calmet)\nThis advantage was derived from tribulation, that the king entered into himself, at least for a time: (Haydock) but he was not constant, ver. 14. After the scourge was withdrawn, he presently relapsed. He had betrayed great cowardice, as even his son confessed; and had probably been treated with great indignity, (Tirinus) as it was the custom with Sesac, or Sesostris, to chain the conquered princes to his triumphal car, and to leave obscene representations of women in the country. (Josephus, viii. 4.) (Herodotus ii.)\nSesostris proceeded to the conquest of Asia. (Tirinus)",
      "commentary_number": "1/1",
      "reading_time": "1 min",
      "source_url": "https://catenabible.com/2chr/12/12",
      "full_content_url": "https://catenabible.com/com/5735e1bcec4bd7c9723bd812",
      "content_type": "full",
      "extraction_method": "beautifulsoup"
    }
  ],
  "methodology": {
    "step_1": "Parse main page with BeautifulSoup for structure",
    "step_2": "Extract metadata (author, period, reading time)",
    "step_3": "Use Firecrawl to get full content from 'Go to Commentary' links",
    "step_4": "Fallback to BeautifulSoup for accordion content if needed",
    "result": "Successfully captured 2CHR 12:12",
    "advantages": [
      "Complete commentary content via Firecrawl",
      "Structured metadata extraction",
      "Robust fallback mechanisms",
      "Records verses even without commentaries for complete tracking"
    ]
  }
}