{
  "verse_reference": "PS 20:9",
  "book": "ps",
  "chapter": 20,
  "verse": 9,
  "commentary_status": "available",
  "total_commentaries": 1,
  "commentaries": [
    {
      "author": "Augustine of Hippo",
      "period": "AD430",
      "content": "10. \"O Lord, save the King:\" that He, who in His Passion hath shown us an example of conflict, should also offer up our sacrifices, the Priest raised from the dead, and established in heaven. \"And hear us in the day when we shall call on Thee\" (ver. 9). And as He now offereth for us, \"hear us in the day when we shall call on Thee.\""
    }
  ]
}