{
  "verse_reference": "PS 89:21",
  "book": "ps",
  "chapter": 89,
  "verse": 21,
  "commentary_status": "available",
  "total_commentaries": 1,
  "commentaries": [
    {
      "author": "Augustine of Hippo",
      "period": "AD430",
      "content": "1 Esdras Wisdom of Solomon Wisdom of Sirach Epistle of Jeremiah Prayer of Manasseh With whom my hand shall be established: my arm also shall strengthen him. Augustine of Hippo 21. \"My hand shall hold Him fast, and My arm shall strengthen Him\" (ver. 21): because there was a taking up of man; because flesh was assumed in the Virgin's womb, because by Him who in the form of God is coequal with the Father, the form of a servant was taken, and He became obedient unto death, even the death of the Cross."
    }
  ]
}