{
  "verse_reference": "GN 11:6",
  "book": "gn",
  "chapter": 11,
  "verse": 6,
  "commentary_status": "available",
  "total_commentaries": 1,
  "commentaries": [
    {
      "author": "George Leo Haydock",
      "period": "AD1849",
      "content": "1 Esdras Wisdom of Solomon Wisdom of Sirach Epistle of Jeremiah Prayer of Manasseh And the LORD said, Behold, the people are one, and they have all one language; and this they begin to do: and now nothing will be restrained from them, which they have imagined to do. This seems to be spoken ironically; though the effects of weak mortals, the sons of Adam, when pursued with vigour and unanimity, will produce great effects. These builders had conceived an idea of raising the tower as high as possible, hyperbolically, to touch heaven."
    }
  ]
}