{
  "verse_reference": "ACTS 19:26",
  "commentaries": [
    {
      "author": "John Chrysostom",
      "period": "AD407",
      "content_pt": "Ele reverte, diz ele, nosso ofício: (e) Deste trabalho temos nossa riqueza. Ele persuadiu. Como ele persuadiu— ele, um homem de consideração medíocre? Como prevalecer sobre tão grande força de hábito? Fazendo o quê— dizendo o quê? Não cabe a um Paulo (efetuar isso), não cabe a um homem. Mesmo isso é suficiente, que ele disse: Eles não são deuses. Agora, se a impiedade (das religiões pagãs) era tão fácil de detectar, deveria ter sido condenada há muito tempo: se era forte, não deveria ter sido derrubada tão rapidamente. (b) Pois, para que não considerem dentro de si mesmos (quão estranho), que um ser humano deveria ter tal poder como este, e se um ser humano tem poder para efetuar tais coisas, então deve-se ser persuadido por aquele homem, ele acrescenta: (f) não apenas nosso ofício está em perigo de ser desprezado, mas também, como se alegando uma consideração maior, o templo da grande deusa Diana, etc. (c) a quem toda a Ásia e o mundo adoram."
    },
    {
      "author": "Peter of Alexandria",
      "period": "AD311",
      "content_pt": "Pois em Éfeso também agarraram Gaio e Aristarco em vez de Paulo, e apressaram-se para o teatro, sendo estes companheiros de viagem de Paulo."
    }
  ]
}