{
  "verse_reference": "ACTS 22:2",
  "commentaries": [
    {
      "author": "John Chrysostom",
      "period": "AD407",
      "content_pt": "(E quando ouviram que ele lhes falava na língua hebraica, guardaram ainda mais silêncio; e ele disse,) Observais como o uso da mesma língua os subjugou. De fato, eles tinham uma espécie de temor por aquela língua. Observai também como ele prepara o caminho para seu discurso, começando assim: Eu sou verdadeiramente um homem que é judeu, nascido em Tarso, uma cidade da Cilícia, e, no entanto, criado nesta cidade aos pés de Gamaliel, e ensinado segundo a perfeita maneira da lei dos pais, e fui zeloso para com Deus, como todos vós sois hoje."
    }
  ]
}