{
  "verse_reference": "ACTS 9:16",
  "verse_text": "Verse text for ACTS 9:16",
  "scraped_with": "Hybrid approach (Firecrawl + BeautifulSoup)",
  "extraction_date": "2025-09-11",
  "source_url": "https://catenabible.com/acts/9/16",
  "commentary_status": "available",
  "total_commentaries": 1,
  "full_content_fetched": 1,
  "commentaries": [
    {
      "author": "John Chrysostom",
      "period": "AD407",
      "content": "Not only, says He, shall he be a believer, but even a teacher, and great boldness shall he show: 'before Gentiles and kings'— such shall be the spread of the doctrine!— that just as He astonished (him) by the former, so He may (startle him even more) by the latter. And Ananias went, and entered into the house, and laid his hands upon him, and said, Brother Saul— he straightway addresses him as a friend by that name— Jesus, Who appeared unto you in the way in which you came— and yet Christ had not told him this, but he learned it from the Spirit— has sent me unto you, that you may receive your sight, and be filled with the Holy Ghost.",
      "commentary_number": "1/1",
      "reading_time": "1 min",
      "source_url": "https://catenabible.com/acts/9/16",
      "full_content_url": "https://catenabible.com/com/58cf03f5dec071662b7b9277",
      "content_type": "full",
      "extraction_method": "beautifulsoup"
    }
  ],
  "methodology": {
    "step_1": "Parse main page with BeautifulSoup for structure",
    "step_2": "Extract metadata (author, period, reading time)",
    "step_3": "Use Firecrawl to get full content from 'Go to Commentary' links",
    "step_4": "Fallback to BeautifulSoup for accordion content if needed",
    "result": "Successfully captured ACTS 9:16",
    "advantages": [
      "Complete commentary content via Firecrawl",
      "Structured metadata extraction",
      "Robust fallback mechanisms",
      "Records verses even without commentaries for complete tracking"
    ]
  }
}