{
  "verse_reference": "2KGS 24:14",
  "book": "2kgs",
  "chapter": 24,
  "verse": 14,
  "commentary_status": "available",
  "total_commentaries": 1,
  "commentaries": [
    {
      "author": "George Leo Haydock",
      "period": "AD1849",
      "content": "1 Esdras Wisdom of Solomon Wisdom of Sirach Epistle of Jeremiah Prayer of Manasseh And he carried away all Jerusalem, and all the princes, and all the mighty men of valor, even ten thousand captives, and all the craftsmen and smiths: none remained, except the poorest sort of the people of the land. All; the chief men, chap. Ezechiel and Mardocheus were in the number. The first term means a workman in wood, stone; the latter seems to designate a mason, smith, or garrison-soldier; (Calmet) or one expert in making camps; (Sa) an engineer. (Tirinus) St. Jerome explains it of one who enchases jewels in gold. (Menochius) Hecateus and Demetrius (ap. and Clement of Alexandria) mention this transportation."
    }
  ]
}