{
  "verse_reference": "EZR 5:8",
  "book": "ezr",
  "chapter": 5,
  "verse": 8,
  "commentary_status": "available",
  "total_commentaries": 1,
  "commentaries": [
    {
      "author": "George Leo Haydock",
      "period": "AD1849",
      "content": "1 Esdras Wisdom of Solomon Wisdom of Sirach Epistle of Jeremiah Prayer of Manasseh Be it known unto the king, that we went into the province of Judea, to the house of the great God, which is built with great stones, and timber is laid in the walls, and this work goes on diligently , and prospers in their hands. Protestants, \"great. \"(Haydock) Hebrew, \"to be rolled. \"See Vitruv. Septuagint, \"choice stones. \"Kimchi, \"marble. \"(Calmet) 3 Esdras, \"polished and precious stones. \"(Haydock) Yet the Vulgate seems more conformable to chap. , and Aggeus ii. (Menochius) (Ribera) Walls, every fourth course, 3 Kings vi."
    }
  ]
}