{
  "verse_reference": "GN 13:5",
  "verse_text": "Verse text for GN 13:5",
  "scraped_with": "Hybrid approach (Firecrawl + BeautifulSoup)",
  "extraction_date": "2025-09-17",
  "source_url": "https://catenabible.com/gn/13/5",
  "commentary_status": "available",
  "total_commentaries": 2,
  "full_content_fetched": 2,
  "commentaries": [
    {
      "author": "Ambrose of Milan",
      "period": "AD397",
      "content": "It remains to be seen if Lot too, his nephew, was rich as one who belonged to the same family. But Scripture says only that he had many cattle. In fact, the text reads, “Lot also, who went with Abraham, had flocks, herds and tents.” He had no silver, because he was not yet just; in fact, “the tongue of the just man is like silver purified by fire.” He had no gold, which was the possession of the one who saw the posterity of Christ, of whom it is written: “And his posterity shines like gold.” Abraham saw him, as the Lord testified when he said, “Abraham saw my day and rejoiced.” This is why he deserved to shine like gold and to have gold as his endowment. .",
      "commentary_number": "1/2",
      "reading_time": "1 min",
      "source_url": "https://catenabible.com/gn/13/5",
      "full_content_url": "https://catenabible.com/com/5838d64c205c248f42e519fe",
      "content_type": "full",
      "extraction_method": "beautifulsoup"
    },
    {
      "author": "Ambrose of Milan",
      "period": "AD397",
      "content": "It is impossible for me to omit here a discussion of a question that has stumped even the more learned, namely, why the text is worded this way: “Lot also, who went with Abraham,” as though we were to understand that there was another Lot who did not go with him. And many believe the problem is as yet unresolved. So to satisfy these and at the same time to abide by the rule of Scripture, we would say that there is one person who takes on two roles, that in one and the same individual two things are signified. Numerically Lot is a single individual; virtually he is two. In fact, Lot, according to the Latin interpretation, means declinatio (“a deviation”). But one can deviate either from the good or from the bad. So when Lot deviated from the bad, that is, from error, from base and criminal behavior, he was joined to his uncle. When he deviated from the good, that is, from what is just, innocent, holy and sacred, he was joined to baseness. This is why it says, “now Lot too, who accompanied Abraham,” because he had not yet chosen Sodom, and he was not dwelling among those who are authors of evil. Thereafter he did go to live in Sodom. And so it was that he became alienated from himself; he thought of himself as of another, as of one, that is, who withdraws not only from the just man but even from himself.",
      "commentary_number": "2/2",
      "reading_time": "1 min",
      "source_url": "https://catenabible.com/gn/13/5",
      "full_content_url": "https://catenabible.com/com/5838d64c205c248f42e519ff",
      "content_type": "full",
      "extraction_method": "firecrawl"
    }
  ],
  "methodology": {
    "step_1": "Parse main page with BeautifulSoup for structure",
    "step_2": "Extract metadata (author, period, reading time)",
    "step_3": "Use Firecrawl to get full content from 'Go to Commentary' links",
    "step_4": "Fallback to BeautifulSoup for accordion content if needed",
    "result": "Successfully captured GN 13:5",
    "advantages": [
      "Complete commentary content via Firecrawl",
      "Structured metadata extraction",
      "Robust fallback mechanisms",
      "Records verses even without commentaries for complete tracking"
    ]
  }
}