{
  "verse_reference": "MK 8:6",
  "book": "mk",
  "chapter": 8,
  "verse": 6,
  "commentary_status": "available",
  "total_commentaries": 1,
  "commentaries": [
    {
      "author": "Augustine of Hippo",
      "period": "AD430",
      "content": "And he commanded the people to sit down on the ground: and he took the seven loaves, and gave thanks, and broke them, and gave them to his disciples to set before them; and they did set them before the people. Augustine of Hippo In expounding holy Scriptures, I am, so to speak, now breaking bread for you. If you hunger to receive it, your heart will sing out with the fullness of praise. And if you are thus made rich in your banquet, why would you then be niggardly in good works and deeds of mercy. What I am distributing to you is not my own. What you feast upon, I also feast upon."
    }
  ]
}