{
  "verse_reference": "REV 7:16",
  "verse_text": "Verse text for REV 7:16",
  "scraped_with": "Hybrid approach (Firecrawl + BeautifulSoup)",
  "extraction_date": "2026-03-14",
  "source_url": "https://catenabible.com/rv/7/16",
  "commentary_status": "available",
  "total_commentaries": 2,
  "full_content_fetched": 2,
  "commentaries": [
    {
      "author": "Bede",
      "period": "AD735",
      "content": "hunger: This it is which the Lord Himself promised, saying, \"I am the bread of life: he who cometh to Me shall never hunger; and he who believeth in Me shall never thirst.\" Yea, \"Blessed are they who hunger and thirst after righteousness, for they shall be filled.\"",
      "commentary_number": "1/2",
      "reading_time": "< 1 min",
      "source_url": "https://catenabible.com/rv/7/16",
      "full_content_url": "https://catenabible.com/com/5862e9b6dd1bb6dd3dba9bda",
      "content_type": "full",
      "extraction_method": "beautifulsoup"
    },
    {
      "author": "Bede",
      "period": "AD735",
      "content": "the sun: \"We passed,\" he says, \"through fire and water, and thou broughtest us out into a place of refreshment.\" <a",
      "commentary_number": "2/2",
      "reading_time": "< 1 min",
      "source_url": "https://catenabible.com/rv/7/16",
      "full_content_url": "https://catenabible.com/com/5862e9b6dd1bb6dd3dba9bdb",
      "content_type": "full",
      "extraction_method": "beautifulsoup"
    }
  ],
  "methodology": {
    "step_1": "Parse main page with BeautifulSoup for structure",
    "step_2": "Extract metadata (author, period, reading time)",
    "step_3": "Use Firecrawl to get full content from 'Go to Commentary' links",
    "step_4": "Fallback to BeautifulSoup for accordion content if needed",
    "result": "Successfully captured REV 7:16",
    "advantages": [
      "Complete commentary content via Firecrawl",
      "Structured metadata extraction",
      "Robust fallback mechanisms",
      "Records verses even without commentaries for complete tracking"
    ]
  }
}